README.md
setup.cfg
setup.py
radioactive/__init__.py
radioactive/model.py
radioactive/qt.py
radioactive.egg-info/PKG-INFO
radioactive.egg-info/SOURCES.txt
radioactive.egg-info/dependency_links.txt
radioactive.egg-info/top_level.txt