Metadata-Version: 1.1
Name: radioactive
Version: 0.0.1
Summary: Reactive python structures
Home-page: https://github.com/tiagocoutinho/radioactive
Author: Tiago Coutinho
Author-email: coutinhotiago@gmail.com
License: MIT license
Keywords: reactive
Platform: UNKNOWN
Classifier: Development Status :: 2 - Pre-Alpha
Classifier: Intended Audience :: Developers
Classifier: License :: OSI Approved :: MIT License
Classifier: Natural Language :: English
Classifier: Programming Language :: Python :: 3
Classifier: Programming Language :: Python :: 3.6
Classifier: Programming Language :: Python :: 3.7
